SimpleEncoder/SimpleEncode.py
SimpleEncoder/__init__.py
SimpleEncoder/config.py
SimpleEncoder/decode.py
SimpleEncoder/encode.py
SimpleEncoder/hash.py
SimpleEncoder/validator.py
SimpleEncoder-0.0.3.dist-info/METADATA
SimpleEncoder-0.0.3.dist-info/WHEEL
SimpleEncoder-0.0.3.dist-info/license
SimpleEncoder-0.0.3.dist-info/top_level.txt
SimpleEncoder-0.0.3.dist-info/RECORD
