Metadata-Version: 2.1
Name: SimpleEncoder
Version: 0.0.3
Summary: Simple and fast data encoding.
Home-page: https://github.com/SikWeet/SimpleEncode/tree/main
Author: Xpeawey
Author-email: girectx@gmail.com
Project-URL: GitHub, https://github.com/SikWeet
Keywords: simple encoder,pypi simple encode,encoder,pypi encoding,simpleEncoder
Classifier: Programming Language :: Python :: 3.11
Classifier: License :: OSI Approved :: MIT License
Classifier: Operating System :: OS Independent
Requires-Python: >=3.6
License-File: license
